[
  {
    "id": 1,
    "name": "Sunny Downtown Townhouse",
    "description": "A beautiful townhouse in the heart of downtown with plenty of natural light.",
    "photoUrls": [
      "https://example.com/apartment1_1.jpg",
      "https://example.com/apartment1_2.jpg"
    ],
    "amenities": ["AirConditioning", "WasherDryer", "Garage"],
    "beds": 4,
    "baths": 3,
    "squareFeet": 1870,
    "propertyType": "Townhouse",
    "postedDate": "2023-05-15T00:00:00Z",
    "locationId": 1,
    "hoaFee": 150.00,
    "purchasePrice": 450000.00,
    "estimatedValue": 475000.00,
    "ownerId": 1
  },
  {
    "id": 2,
    "name": "Cozy Old Town Home",
    "description": "A charming old town home with a peaceful neighborhood.",
    "photoUrls": [
      "https://example.com/beachhouse1.jpg",
      "https://example.com/beachhouse2.jpg"
    ],
    "amenities": ["AirConditioning", "WasherDryer", "Parking", "Pool"],
    "beds": 5,
    "baths": 4.5,
    "squareFeet": 1200,
    "propertyType": "SingleFamily",
    "postedDate": "2023-06-01T00:00:00Z",
    "locationId": 2,
    "hoaFee": 170.00,
    "purchasePrice": 550000.00,
    "estimatedValue": 575000.00,
    "ownerId": 1
  },
  {
    "id": 3,
    "name": "Modern City Townie",
    "description": "Sleek and stylish loft in the heart of the city.",
    "photoUrls": [
      "https://example.com/cityloft1.jpg",
      "https://example.com/cityloft2.jpg"
    ],
    "amenities": ["AirConditioning", "WasherDryer", "Gym"],
    "beds": 2,
    "baths": 2,
    "squareFeet": 1200,
    "propertyType": "Townhouse",
    "postedDate": "2023-07-01T00:00:00Z",
    "locationId": 3,
    "hoaFee": 1170.00,
    "purchasePrice": 1550000.00,
    "estimatedValue": 975000.00,
    "ownerId": 2
  }
]
